{"data":{"site":{"siteMetadata":{"title":"童话说","keywords":["tonghuashuo","github","front-end","javascript","typescript","react","node","washington","hua","童话","童话说","前端","博客","技术","计算机","互联网"]}},"allMarkdownRemark":{"totalCount":58,"edges":[{"node":{"id":"730b99c7-1786-5732-996d-7e988979e77a","frontmatter":{"title":"新阅","description":"在线视频协作平台","from":"2017-08-01","to":"2017-10-01","tags":null,"cover":{"publicURL":"/static/xinyue-64b35564f5bc639232b66b6559065b31.jpg"},"series":null,"draft":false},"fields":{"slug":"/project/xinyue","type":"project","date":null},"excerpt":"新阅简介一个专为视频行业设计的在线协同平台，主要功能包括：文件云存储、分享、评论、标注、版本控制、多功能播放器等。项目使用 React 全家桶进行开发。其中一个功能点为对视频关键帧进行手绘标注，我们通过创建多个离屏 Canvas…"}},{"node":{"id":"52c14666-2e1f-5d9d-8200-41713b54c39a","frontmatter":{"title":"FBC","description":"FBC 会员服务 Web App","from":"2017-04-01","to":"2017-06-01","tags":null,"cover":{"publicURL":"/static/fbc-73b8b250e607c97c493edf1b542345fa.jpg"},"series":null,"draft":false},"fields":{"slug":"/project/fbc","type":"project","date":null},"excerpt":"FBC简介FBC 会员服务 Web App，设计用于微信端，会员可通过该 App 进行会议室预约、吧台自助消费等会员服务。基于 Vue 2.x 开发的 SPA，基于 Axios 封装了 HTTP 客户端，使用 SCSS + PostCSS 编写样式，使用 Karma…"}},{"node":{"id":"e66d25c0-b3d3-5be1-b1ce-8b3cc5796db0","frontmatter":{"title":"INEX 影力所","description":"影力所 - 一个基于影响力的数字资产交易所","from":"2018-01-01","to":"","tags":null,"cover":{"publicURL":"/static/inex-d05e35007bfc7486b76be1dbf9c52aa8.jpg"},"series":null,"draft":false},"fields":{"slug":"/project/inex","type":"project","date":null},"excerpt":"INEX 影力所简介影力所（INEX，Influence Exchange）是一个基于影响力的数字资产交易所，使用平台币 INC 作为流通的基本货币。影响力被货币化后，可以和 INC 进行对价，并在影力所中进行投资交易。项目基于 React 1…"}},{"node":{"id":"ffd2167f-246b-54a5-8ac1-75e907753ef5","frontmatter":{"title":"Xshowroom 买手圈","description":"国内时尚业首个专业买手服务平台","from":"2016-03-01","to":"2017-03-01","tags":null,"cover":{"publicURL":"/static/xshowroom-72ea2ae7921cb5aa0b3b4f56578ed2b9.jpg"},"series":null,"draft":false},"fields":{"slug":"/project/xshowroom","type":"project","date":null},"excerpt":"Xshowroom 买手圈简介国内时尚业首个专业买手服务平台，基于 AngularJS 开发。项目接手自前任团队，接手时所用技术栈为手写 CSS，且没有任何的依赖管理和自动化构建流。自接手，我引入了 SASS 进行 CSS 的模块化，使用 Gulp…"}},{"node":{"id":"37f30f7b-2376-50c9-8c2a-8fe846edca7c","frontmatter":{"title":"使用 Sublime Text 编写 LaTeX","description":"用你最熟悉的工具来写 LaTeX 吧","from":null,"to":null,"tags":["sublime","latex"],"cover":{"publicURL":"/static/latex-with-sublime-text-e7689b7e9fe6160a6ed614a10125ca29.jpg"},"series":"","draft":false},"fields":{"slug":"/blog/2015/04/01/latex-with-sublime-text","type":"blog","date":"2015-03-31T16:00:00.000Z"},"excerpt":"为什么要用 Sublime Text大部分的 LaTeX 教程都会推荐使用 WinEdt、TexMake…"}},{"node":{"id":"25b37368-41f1-54c9-ba43-ec5713bfa22f","frontmatter":{"title":"栈计算器","description":"通过“栈”实现的方程式计算器","from":null,"to":null,"tags":["stack","calculator","algorithm","project"],"cover":{"publicURL":"/static/stack-calculator-256bbf9439e7f58974c946bc16f54832.jpg"},"series":"","draft":false},"fields":{"slug":"/blog/2015/02/10/stack-calculator","type":"blog","date":"2015-02-09T16:00:00.000Z"},"excerpt":"简单说两句用栈实现计算器，这是数据结构中关于栈的一个经典案例，在很多数据结构的教材中也都有明确的算法说明。这里我们给出一个用 JavaScript…"}},{"node":{"id":"a0ed4de0-1274-5b2a-89d0-71c1224f46a2","frontmatter":{"title":"时间是什么颜色的","description":"如果时间有颜色……","from":null,"to":null,"tags":["color","time","project"],"cover":{"publicURL":"/static/tik-tok-color-03c874556dd31d9db5f30b7609751b92.jpg"},"series":"","draft":false},"fields":{"slug":"/blog/2015/02/11/tik-tok-color","type":"blog","date":"2015-02-10T16:00:00.000Z"},"excerpt":"简单说两句最初在 这里 看到了这个案例，觉得挺有意思的，就尝试自己仿制了一个。原理上讲其实很简单，将时间的值对应为颜色通道的数值，并通过视觉效果体现出来。原作仅为 RGB 模式，我在其基础之上还尝试了 HSL 模式和 CMYK 的效果，并支持 3 种模式之间的切换查看。CMYK…"}},{"node":{"id":"b911a2ba-1a78-5e45-b478-a51b23716f96","frontmatter":{"title":"MIUI 图标缓存问题","description":"离奇失踪的图标","from":null,"to":null,"tags":["android","miui","icon","cache"],"cover":{"publicURL":"/static/miui-icon-cache-2e66c31a61d5319c1849ea082e8c80ee.jpg"},"series":"","draft":false},"fields":{"slug":"/blog/2015/04/18/miui-icon-cache","type":"blog","date":"2015-04-17T16:00:00.000Z"},"excerpt":"问题描述为 Android 应用替换图标是一件非常容易的事，只需要替换 ic_launcher.png 即可，但在 MIUI…"}},{"node":{"id":"85368b4d-09c3-5b67-9184-f42d71f218cf","frontmatter":{"title":"纯 CSS3 绘制月饼","description":"中秋佳节，用CSS3来画个月饼吧","from":null,"to":null,"tags":["css","mooncake","project"],"cover":{"publicURL":"/static/css3-mooncake-9aaefaae86216c79623893c080f1ccc2.jpg"},"series":"","draft":false},"fields":{"slug":"/blog/2015/09/27/css3-mooncake","type":"blog","date":"2015-09-26T16:00:00.000Z"},"excerpt":"用 CSS3 绘图并不是什么新鲜事，业内有很多大牛都已经尝试过。借着中秋，我们就来画个月饼试试吧。PS：考虑到我并非学美术出身，美观度方面还请各位多多包涵。PPS：建议使用 Chrome 浏览器（或其它 webkit、blink…"}},{"node":{"id":"a8a6daf3-3a22-5af9-a578-6874608ea602","frontmatter":{"title":"substr() 和 substring() 的区别","description":"两个函数，傻傻分不清楚","from":null,"to":null,"tags":["javascript","substr","substring","slice"],"cover":{"publicURL":"/static/substring-289ad52fc38963e15549cd1dc24678e4.jpg"},"series":"","draft":false},"fields":{"slug":"/blog/2015/05/15/substr-and-substring","type":"blog","date":"2015-05-14T16:00:00.000Z"},"excerpt":"JavaScript 中有两个非常常用但又非常容易混淆的函数：  和  ，两者都是 String 类型的方法，作用都是返回目标字符串的一个子串。关于两者的详细文档可以参考：[MDN] String.prototype.substr 和 [MDN] String.prototype…"}},{"node":{"id":"0d7d5280-b38d-5f19-807b-50e4ad97e6a8","frontmatter":{"title":"每天一点ES6(2)：let 和 const","description":"终于，JavaScript 也能用上块级作用域和常量了","from":null,"to":null,"tags":["ecmascript","2015","es6","javascript","let","const"],"cover":{"publicURL":"/static/es6daily-0950334fb8899f1006423341cbfeecb9.jpg"},"series":"es6daily","draft":false},"fields":{"slug":"/blog/2016/01/25/es6-daily-02-let-and-const","type":"blog","date":"2016-01-24T16:00:00.000Z"},"excerpt":"letES6 新增了  命令，用于声明变量，和  类似，区别在于用  声明的变量只在  所在的代码块内有效，不存在声明提前。因此当用  声明变量时，必须像在 Java/C++ 中那样，先声明后使用。（其实即便是在 ES…"}},{"node":{"id":"af821c36-0f12-5efe-b5cb-180be0c19e7e","frontmatter":{"title":"每天一点ES6(1)：概述","description":"伊艾斯6大法好，每天一点不会老！","from":null,"to":null,"tags":["ecmascript","2015","es6","javascript"],"cover":{"publicURL":"/static/es6daily-0950334fb8899f1006423341cbfeecb9.jpg"},"series":"es6daily","draft":false},"fields":{"slug":"/blog/2016/01/24/es6-daily-01-intro","type":"blog","date":"2016-01-23T16:00:00.000Z"},"excerpt":"本系列是对阮一峰老师的开源著作 《ES6 标准入门》 的学习笔记，通过博客的方式强迫自己将学到的东西解释给别人听，进而加深认识，同时也算为推广ES6贡献一点绵薄之力吧。ES6是啥？ECMAScript 6（简称ES6）是 JavaScript 的最新标准，发布于 2015 年…"}},{"node":{"id":"8351062a-4d59-505e-9dd8-04defab9ec38","frontmatter":{"title":"电梯调度算法","description":"上上下下的感受","from":null,"to":null,"tags":["elevator","algorithm","project"],"cover":{"publicURL":"/static/elevator-7b7f4cefe4c7bf293ff2cdb266af33d9.jpg"},"series":"","draft":false},"fields":{"slug":"/blog/2016/02/16/elevator","type":"blog","date":"2016-02-15T16:00:00.000Z"},"excerpt":"起源之所以会想到这么个主题，纯粹是因为前两天坐电梯的时候，脑子里某条神经炸出来一团莫名的火花。灵感这东西，不定什么时候说来就来。SCAN 调度算法电梯调度的核心是 SCAN…"}},{"node":{"id":"7c784293-e81f-5b97-a872-2746300a0a89","frontmatter":{"title":"每天一点ES6(6)：正则的扩展","description":"四字节 Unicode 的春天","from":null,"to":null,"tags":["ecmascript","2015","es6","javascript","regular","expression","regexp"],"cover":{"publicURL":"/static/es6daily-0950334fb8899f1006423341cbfeecb9.jpg"},"series":"es6daily","draft":false},"fields":{"slug":"/blog/2016/04/06/es6-daily-06-regexp","type":"blog","date":"2016-04-05T16:00:00.000Z"},"excerpt":"终于这回不打脸了难得日更了，这一回来讲正则。当然，这不是正则的基础教学，我们只关心 ES6 为 JavaScript 的正则带来的变化。RegExp 构造函数ES5 中，构造函数  的参数有两种形式：ES…"}},{"node":{"id":"62111535-c056-5418-a53e-50726b782899","frontmatter":{"title":"每天一点ES6(7)：数值的扩展","description":"每一个数字都不能放过","from":null,"to":null,"tags":["ecmascript","2015","es6","javascript","number"],"cover":{"publicURL":"/static/es6daily-0950334fb8899f1006423341cbfeecb9.jpg"},"series":"es6daily","draft":false},"fields":{"slug":"/blog/2016/04/12/es6-daily-07-number","type":"blog","date":"2016-04-11T16:00:00.000Z"},"excerpt":"二进制和八进制表示法ES6 提供了二进制和八进制数的新写法，分别用前缀  （零必）和  （零欧）表示。ES5 开始，严格模式下就不再允许使用前缀  ，ES6 进一步明确必须使用前缀  。如果要将  和  前缀的字符串数值专为十进制，可以用  方法。旧酒装进了新瓶子ES…"}},{"node":{"id":"f42503ed-27f4-54af-b22f-71a8b90ed82c","frontmatter":{"title":"每天一点ES6(8)：数组的扩展","description":"别拿语法糖不当干粮","from":null,"to":null,"tags":["ecmascript","2015","es6","javascript","array"],"cover":{"publicURL":"/static/es6daily-0950334fb8899f1006423341cbfeecb9.jpg"},"series":"es6daily","draft":false},"fields":{"slug":"/blog/2016/07/26/es6-daily-08-array","type":"blog","date":"2016-07-25T16:00:00.000Z"},"excerpt":"久违了的更新不知不觉几个月就过去了，终于想到要更新了，下一次又不知道要等到什么时候了，毕竟连猴年马月都过去了……这一回我们来说说 ES6 中的数组。其实数组方面并没有太多实质性的改变，更多的是一些语法糖，对 ES…"}},{"node":{"id":"53b0a6a5-7b05-5d43-af41-496a6e305dbc","frontmatter":{"title":"每天一点ES6(3)：解构赋值","description":"让你一次赋个够","from":null,"to":null,"tags":["ecmascript","2015","es6","javascript","destructuring"],"cover":{"publicURL":"/static/es6daily-0950334fb8899f1006423341cbfeecb9.jpg"},"series":"es6daily","draft":false},"fields":{"slug":"/blog/2016/02/02/es6-daily-03-destructuring","type":"blog","date":"2016-02-01T16:00:00.000Z"},"excerpt":"什么叫解构所谓 解构（Destructuring） ，就是把数组或对象打散为一堆变量。解构是 构造（Constructuring…"}},{"node":{"id":"fe5c066d-1711-595c-a192-c284934f6245","frontmatter":{"title":"每天一点ES6(5)：字符串的扩展","description":"不变的字符串现在更加多变了","from":null,"to":null,"tags":["ecmascript","2015","es6","javascript","string"],"cover":{"publicURL":"/static/es6daily-0950334fb8899f1006423341cbfeecb9.jpg"},"series":"es6daily","draft":false},"fields":{"slug":"/blog/2016/04/05/es6-daily-05-string","type":"blog","date":"2016-04-04T16:00:00.000Z"},"excerpt":"继续打脸呵呵呵呵呵，现在这个系列已经正式沦落为连作者也不知道啥时候更的节奏了……这次来讲讲字符串，ES6对  类扩展了一些函数，使得操作字符串更加的便捷，一些以往必须借助额外的 Javascript 代码才能实现的效果，现在有了现成的函数。改进的 Unicode…"}},{"node":{"id":"58afc609-3cbe-59f2-9463-b1c8a9fb0fb9","frontmatter":{"title":"每天一点ES6(4)：Babel","description":"《圣经》的光辉，永恒！","from":null,"to":null,"tags":["ecmascript","2015","es6","javascript","babel","npm"],"cover":{"publicURL":"/static/es6daily-0950334fb8899f1006423341cbfeecb9.jpg"},"series":"es6daily","draft":false},"fields":{"slug":"/blog/2016/02/19/es6-daily-04-babel","type":"blog","date":"2016-02-18T16:00:00.000Z"},"excerpt":"打脸好吧，这个系列已经从一开始的日更变成现在周更都未必做得到了，啪！啪！啪！打脸呐！！！好，打脸完毕，下面我们来说正事儿。ES6 无限好，就是用不了尽管 ES6 发布有一阵子了，但各大浏览器的兼容工作才刚刚开始，最新版的 Chrome、Firefox、Safari 对 ES…"}},{"node":{"id":"4a1d2e7d-2479-544f-bb08-fb40508922a2","frontmatter":{"title":"5 分钟彻底明白 JSONP","description":"说穿了，其实没那么难","from":null,"to":null,"tags":["javascript","jsonp"],"cover":{"publicURL":"/static/jsonp-f8f2d118b15646398f7d00e19eb17ff9.jpg"},"series":"","draft":false},"fields":{"slug":"/blog/2016/08/17/jsonp","type":"blog","date":"2016-08-16T16:00:00.000Z"},"excerpt":"JSONP全称 JSON with Padding，用于解决AJAX跨域问题的一种方案（关于“同源策略”的具体内容这里就不赘述了，度娘足矣）本着实用优先的原则，我们先给方案，再讲原理，赶时间的朋友只要看完下一节就可以了，想了解细节的可以顺序往下看完。用 jQuery…"}},{"node":{"id":"d304fd51-3c44-562e-83d6-4f38f86fba46","frontmatter":{"title":"解决 macOS 下 MySQL 2002 错误","description":"MySQL 真是个磨人的小妖精","from":null,"to":null,"tags":["mac","mysql","2002"],"cover":{"publicURL":"/static/mysql-error-2002-6f1abf9c085f6538df6bced86e008157.jpg"},"series":"","draft":false},"fields":{"slug":"/blog/2017/02/07/mysql-error-2002","type":"blog","date":"2017-02-06T16:00:00.000Z"},"excerpt":"起因最近在推进公司项目架构的前后端分离，正在做一个 Demo，要用到数据库，结果不知道是不是因为最近一次 macOS 更新的原因，MySQL…"}},{"node":{"id":"c63ffcf4-e190-53c9-8034-3625b105cc44","frontmatter":{"title":"PHP 处理多源 CORS 的解决办法","description":"一个老生常谈的话题，碰到了顺便记录一下","from":null,"to":null,"tags":["php","cors"],"cover":{"publicURL":"/static/cors-77fc63594cf3a06c31921df671acd258.jpg"},"series":"","draft":false},"fields":{"slug":"/blog/2017/03/30/multi-origin-cors-with-php","type":"blog","date":"2017-03-29T16:00:00.000Z"},"excerpt":"CORS 本不是什么新鲜事，也不是特别的难，但最近遇上一个跨域的问题，后端人员是个新手没经验，靠不住，没办法只好自己上。这里权当是个记录。问题其实很简单，PHP 接口层实现 CORS 允许多个指定源访问（局域网地址、应用服务器域名等），直接上代码："}},{"node":{"id":"5aa437b3-5b0c-5fa9-811e-d70e65031bb9","frontmatter":{"title":"iOS 下 click() 无效的问题","description":"iOS这个傲娇的小公举","from":null,"to":null,"tags":["ios","click"],"cover":{"publicURL":"/static/ios-click-f79051a5758b8a973902b2e5d190b714.jpg"},"series":"","draft":false},"fields":{"slug":"/blog/2017/03/31/unable-to-trigger-click-on-ios","type":"blog","date":"2017-03-30T16:00:00.000Z"},"excerpt":"最近用 Vue 做了个项目，其中涉及到头像上传的功能，在 Web 端典型的做法是把文件控件隐藏，然后点击上传按钮时候模拟点击文件控件：在 Vue 中我也如法炮制了一版，在浏览器、Android 下测试都 OK 的，但在 iOS 下  却无法触发。查了下似乎是 iOS…"}},{"node":{"id":"0c9840f6-b257-592c-a6d7-78db32a5e81b","frontmatter":{"title":"记 new Date().toString() 的一个坑","description":"万万没想到，竟在这里踩了个坑……","from":null,"to":null,"tags":["javascript","date","tostring"],"cover":{"publicURL":"/static/date-tostring-e192283893c7e97feb631571134bb805.jpg"},"series":"","draft":false},"fields":{"slug":"/blog/2017/03/08/a-pit-in-date-tostring","type":"blog","date":"2017-03-07T16:00:00.000Z"},"excerpt":"先从问题说起最近接到客户反馈的一个 Bug，说一个页面显示不正常，控制台一开，果然 JS 报错，仔细一看，是项目里用到的 bootstrap-datetime 这么个老牌日期插件报的错。大概意思是说无法调用 undefined 的 slice…"}},{"node":{"id":"ec5406b5-1bd5-5dcb-b368-0f931d5b4e45","frontmatter":{"title":"Webpack \"Invalid Host Header\"","description":"更新有风险，更新需谨慎……","from":null,"to":null,"tags":["webpack","dev","server","invalid","host"],"cover":{"publicURL":"/static/webpack-dev-server-977bc2ebe23a9b6b10fdac4b470847b8.jpg"},"series":"","draft":false},"fields":{"slug":"/blog/2017/05/04/webpack-dev-server-invalid-host-header","type":"blog","date":"2017-05-03T16:00:00.000Z"},"excerpt":"一直以来都在用 Webpack 打包代码，配合 webpack-devserver 作 Hot Module Replacement 感觉棒棒哒，可以专心于程序逻辑，不用被无关紧要的琐事打扰。直到刚才……突如其来的问题正和同事讨论一个技术问题，写了个 Demo…"}},{"node":{"id":"30058c2b-409f-5dd1-8fdf-4b51a048bdf2","frontmatter":{"title":"每天一点ES6(12)：Set 和 Map","description":"多余的，一概不要","from":null,"to":null,"tags":["ecmascript","2015","es6","javascript","map","set"],"cover":{"publicURL":"/static/es6daily-0950334fb8899f1006423341cbfeecb9.jpg"},"series":"es6daily","draft":false},"fields":{"slug":"/blog/2017/07/03/es6-daily-12-set-and-map","type":"blog","date":"2017-07-02T16:00:00.000Z"},"excerpt":"Set，一个独一无二的数组Set 是 ES6 中新增的一种数据类型，可以理解为一种特殊的数组，重点区别在于 Set 的成员值都是唯一的，绝对不会重复。注意到上面代码中最后重复的 5 仅被  了一次，重复的值并未被添加。Set 可以接受一个数组（或其他具有 Iterable…"}},{"node":{"id":"5d980687-2d86-5c6b-a4e3-341149351f40","frontmatter":{"title":"Electron 安装出坑指南","description":"世界本无坑，用的人多了，也就有了坑","from":null,"to":null,"tags":["electron"],"cover":{"publicURL":"/static/electron-a9838665d68ab68d327e48d8720bac3f.jpg"},"series":"","draft":false},"fields":{"slug":"/blog/2017/07/06/electron-install-guide","type":"blog","date":"2017-07-05T16:00:00.000Z"},"excerpt":"ElectronJS 越来越浪了，区区浏览器已经管不了这孩子了，一个没看住，就已经浪到原生客户端的地盘上去了，一边是开着 React Native 去找 iOS 和 Android 搞事情，一边又开着 Electron 想去单挑 WPF 和 Mac…"}},{"node":{"id":"e8c3c93f-2545-5887-8d6d-df513811d1da","frontmatter":{"title":"Node.js 9.0.0 发布","description":"一转眼，又半年过去了","from":null,"to":null,"tags":["nodejs","release"],"cover":{"publicURL":"/static/nodejs-9-release-86f3115cebbb8dd82646ff1d231fa317.jpg"},"series":"","draft":false},"fields":{"slug":"/blog/2017/11/01/nodejs-9-release","type":"blog","date":"2017-10-31T16:00:00.000Z"},"excerpt":"Node.js 发布计划Node.js 从 5.0 开始一直遵循着半年一个大版本的发布周期，每年 4 月左右发布一个主版本号为偶数的 LTS（Long-Term-Support）版本，每年 10 月左右发布一个主版本号为奇数的非 LTS…"}},{"node":{"id":"42ea655c-859e-5d44-93ff-b044e766eeaa","frontmatter":{"title":"每天一点ES6(13)：Proxy 和 Reflect","description":"对不起，有代理真就是可以为所欲为","from":null,"to":null,"tags":["ecmascript","2015","es6","javascript","proxy","reflect"],"cover":{"publicURL":"/static/es6daily-0950334fb8899f1006423341cbfeecb9.jpg"},"series":"es6daily","draft":false},"fields":{"slug":"/blog/2017/12/20/es6-daily-13-proxy-and-reflect","type":"blog","date":"2017-12-19T16:00:00.000Z"},"excerpt":"写在前面又好久没更了，这次来讲的是 ES…"}},{"node":{"id":"2d4faf6f-21e7-5f18-9d1f-106650ab92fb","frontmatter":{"title":"每天一点ES6(14)：Iterator","description":"遍历也能搞出花来，怎么遍历你说了算","from":null,"to":null,"tags":["ecmascript","2015","es6","javascript","iterator","generator"],"cover":{"publicURL":"/static/es6daily-0950334fb8899f1006423341cbfeecb9.jpg"},"series":"es6daily","draft":false},"fields":{"slug":"/blog/2018/02/28/es6-daily-14-iterator","type":"blog","date":"2018-02-27T16:00:00.000Z"},"excerpt":"写在前面这次轮到遍历了。其实 ES5 中就已经有好多种用于遍历的方法：那么这次 ES6 又打算在遍历上搞什么花样劲？Iterator算上 ES6 新引入的数据类型，JavaScript 原生用于表示集合的数据结构就有：Array、Object、Map、Set…"}},{"node":{"id":"e319664e-3730-50ad-8617-5cc0db5a47e6","frontmatter":{"title":"一个非著名前端开发者的 2018","description":"资本寒冬大概是属燕子的吧，一到年末出现","from":null,"to":null,"tags":["summary","2018","2019"],"cover":{"publicURL":"/static/summary-2018-0e9c38c3d5d6b94d53a8dee2a7bdfbae.jpg"},"series":"summary","draft":false},"fields":{"slug":"/blog/2018/12/31/summary-2018","type":"blog","date":"2018-12-30T16:00:00.000Z"},"excerpt":"是的，我还没走2018 年是我参加工作的第三年，过完这个年，我就整三年工龄了。来到上海 3 年，在现东家也待了 3 年。…"}},{"node":{"id":"acaf8789-0319-5c28-881d-fbca9bb89e51","frontmatter":{"title":"每天一点ES6(17)：Async / Await","description":"异步？先等等！","from":null,"to":null,"tags":["ecmascript","2015","es6","javascript","async","await","generator"],"cover":{"publicURL":"/static/es6daily-0950334fb8899f1006423341cbfeecb9.jpg"},"series":"es6daily","draft":false},"fields":{"slug":"/blog/2018/10/06/es6-daily-17-async-await","type":"blog","date":"2018-10-05T16:00:00.000Z"},"excerpt":"又一个异步解决方案ES2015 在异步方面可谓是做足了贡献。之前我们已经介绍过了 Promise，一种可以让我们把异步操作写成链式调用的语法；就在上一篇，我们又介绍了 Generator…"}},{"node":{"id":"f98a2ea0-3ca3-5e0c-80d0-e9a189db678d","frontmatter":{"title":"【译】我们为什么要写 super(props)?","description":"好像知道，又好像不知道","from":null,"to":null,"tags":["react"],"cover":{"publicURL":"/static/overreacted-9fbf74366dc5b9e4aab57572a9f0470d.jpg"},"series":"overreacted","draft":false},"fields":{"slug":"/blog/2019/02/22/why-do-we-write-super-props","type":"blog","date":"2019-02-21T16:00:00.000Z"},"excerpt":"原文地址：Why Do We Write super(props)?原文作者：Dan Abramov我听说 Hooks 最近很火。讽刺的是，我想以一些关于 class 组件的有趣故事来开始这个博客。怎样！（皮一下很开心）这些小坑并不会影响你高效的使用 React…"}},{"node":{"id":"18d5b2c3-e740-57a8-882f-4fe81a809a0a","frontmatter":{"title":"Think in Hooks, Again","description":"忘记过去之所学，我们从头来过","from":null,"to":null,"tags":["react","hooks"],"cover":{"publicURL":"/static/think-in-hooks-26d13ef2591ee05a3c4bba7fc34daa88.jpg"},"series":"","draft":true},"fields":{"slug":"/blog/2019/04/02/think-in-hooks-again","type":"blog","date":"2019-04-01T16:00:00.000Z"},"excerpt":"Again？Why？在 Hooks 刚刚发布之际，官方曾明确表示：我们不打算移除 Class。（至少短期内不会）。大家也不用着急现在就迁移到 Hooks（毕竟变化很大，给大家适应的时间）但未来是属于 Hooks 的。（所以最终你还是会迁移到 Hooks…"}},{"node":{"id":"7d3c2bde-9aac-51c9-855b-a5293a315388","frontmatter":{"title":"说起 React 的生命周期，你或许还不知道……","description":"事情好像没那么简单","from":null,"to":null,"tags":["react","lifecycle"],"cover":{"publicURL":"/static/react-lifecycle-0edf69056144aaf512a28d0670b53b57.jpg"},"series":"","draft":true},"fields":{"slug":"/blog/2019/03/25/react-lifecycle","type":"blog","date":"2019-03-24T16:00:00.000Z"},"excerpt":"写在前面React…"}},{"node":{"id":"e9d9313f-ac38-5f9c-89ba-9f37a14bdb26","frontmatter":{"title":"这该死的数组","description":"常在河边走，哪有不湿鞋","from":null,"to":null,"tags":["array"],"cover":{"publicURL":"/static/think-in-hooks-26d13ef2591ee05a3c4bba7fc34daa88.jpg"},"series":"","draft":true},"fields":{"slug":"/blog/2019/04/08/damn-you-array","type":"blog","date":"2019-04-07T16:00:00.000Z"},"excerpt":"这个世界上有两种数组操作众所周知，在 JavaScript 的世界中有两种数组操作：会改变数组自身的，和会返回新数组的。"}},{"node":{"id":"643fa9a9-9a67-5dd4-9760-f00d46fbdab0","frontmatter":{"title":"为变化而设计","description":"世上唯一不变的，就是变化本身","from":null,"to":null,"tags":["coding"],"cover":{"publicURL":"/static/think-in-hooks-26d13ef2591ee05a3c4bba7fc34daa88.jpg"},"series":"","draft":true},"fields":{"slug":"/blog/2019/04/09/design-for-change","type":"blog","date":"2019-04-08T16:00:00.000Z"},"excerpt":"专业和业余的区别前端的低门槛，给很多人留下了「这是个能速成的高薪岗位」的印象，自学一个星期就能上手，一个月就能达到 6…"}},{"node":{"id":"74fb6718-91f9-57db-9f87-d675e67d3eae","frontmatter":{"title":"favicon 2019","description":"","from":null,"to":null,"tags":["favicon"],"cover":{"publicURL":"/static/react-lifecycle-0edf69056144aaf512a28d0670b53b57.jpg"},"series":"","draft":true},"fields":{"slug":"/blog/2019/05/05/favicon","type":"blog","date":"2019-05-04T16:00:00.000Z"},"excerpt":""}},{"node":{"id":"a8848647-964c-5d24-ac4e-097d4c54aa89","frontmatter":{"title":"每天一点ES6(9)：函数的扩展","description":"博采众长的实用语法糖","from":null,"to":null,"tags":["ecmascript","2015","es6","javascript","function"],"cover":{"publicURL":"/static/es6daily-0950334fb8899f1006423341cbfeecb9.jpg"},"series":"es6daily","draft":false},"fields":{"slug":"/blog/2016/12/20/es6-daily-09-function","type":"blog","date":"2016-12-19T16:00:00.000Z"},"excerpt":"实用的语法糖ES6 对函数的使用加入了不少比较实用的新特性，虽说依然还是语法糖，但确实比较实用的语法糖函数参数默认值ES6 原生支持在函数的参数列表中赋予默认值，当然此前通过在函数实现中对参数进行初始化也能实现同样的效果，但 ES…"}},{"node":{"id":"9dd73037-c954-5ec6-9616-5ae66376c29c","frontmatter":{"title":"每天一点ES6(10)：对象的扩展","description":"迟来的更新……","from":null,"to":null,"tags":["ecmascript","2015","es6","javascript","object"],"cover":{"publicURL":"/static/es6daily-0950334fb8899f1006423341cbfeecb9.jpg"},"series":"es6daily","draft":false},"fields":{"slug":"/blog/2017/04/05/es6-daily-10-object","type":"blog","date":"2017-04-04T16:00:00.000Z"},"excerpt":"迟来的更新想来这个系列上一次更新还是去年年底的时候……真心对不起日更的标题，这个 Flag 立大了……虽然时至今日 ES6 已经不再新鲜，不过自己挖的坑说什么也得填完，这一篇咱继续对象的扩展。ES5 给对象加入了大量实用的方法，用于创建、枚举、封闭一个对象，ES…"}},{"node":{"id":"4c1fa5f9-da88-5bad-b7f1-f133c9b8c211","frontmatter":{"title":"Leetcode 第一刷：Two Sum","description":"都闪开，我要开始装逼了","from":null,"to":null,"tags":["leetcode","two","sum"],"cover":{"publicURL":"/static/leetcode-1aa86b8eea674fca29117e535cfba751.jpg"},"series":"","draft":false},"fields":{"slug":"/blog/2017/04/11/leetcode-01-two-sum","type":"blog","date":"2017-04-10T16:00:00.000Z"},"excerpt":"So，我又来装逼了前端面试不考算法……嗯，对于刚入行的新人这句话或许没啥大毛病，可一旦开始进阶了，算法早晚会成为瓶颈。于是乎，我开始了……新一轮的装逼之旅。周围也有不少刷 Leetcode 的，这货和《编程之美》、《剑指Offer…"}},{"node":{"id":"8b1c0207-54ac-52ba-b9e0-cf822a7605f6","frontmatter":{"title":"每天一点ES6(11)：Symbol","description":"原始类型家族的新成员","from":null,"to":null,"tags":["ecmascript","2015","es6","javascript","symbol"],"cover":{"publicURL":"/static/es6daily-0950334fb8899f1006423341cbfeecb9.jpg"},"series":"es6daily","draft":false},"fields":{"slug":"/blog/2017/07/02/es6-daily-11-symbol","type":"blog","date":"2017-07-01T16:00:00.000Z"},"excerpt":"什么是 SymbolSymbol 是 ES6 中新增的一种原始数据类型，至此 JavsScript 共有 7 种原始数据类型：、、、、、、。注意 array 不是原始数据类型，不要因为可以直接用  定义数组就以为它也是原始数据类型。数组是一种常见的基本数据结构。创建 Symbol…"}},{"node":{"id":"9ed1de84-6ce7-514e-9086-d33e37afa004","frontmatter":{"title":"童话说 V2.0 改版小结","description":"时隔多年，终于换新面貌了","from":null,"to":null,"tags":["blog","2.0","update"],"cover":{"publicURL":"/static/introduction-to-ths-v2-630ee6fc7ad1be564eebffb0e0dd447d.jpg"},"series":"","draft":false},"fields":{"slug":"/blog/2017/08/12/introduction-to-ths-v2","type":"blog","date":"2017-08-11T16:00:00.000Z"},"excerpt":"大更新！！！不知名前端小站“童话说”自创立以来的第一次改版！发布啦！！！大概全世界只有一个人会为此高兴吧……不管，照样庆祝！！！大事记截至本文之前，这个小站共经历了 233 次 commit，距离第一次提交已有 2 年…"}},{"node":{"id":"1c94724f-9638-5acd-9bbc-2902159ff8f8","frontmatter":{"title":"ECMAScript 2017 正式到来","description":"ES 的世界开始日趋平静","from":null,"to":null,"tags":["ecmascript","2017","es8","javascript"],"cover":{"publicURL":"/static/es2017-77b7677386d27526bcb0b2687218f3f1.jpg"},"series":"","draft":false},"fields":{"slug":"/blog/2017/07/12/ecmascript-2017-is-here","type":"blog","date":"2017-07-11T16:00:00.000Z"},"excerpt":"不知不觉的到来自打 ES2015 之后，ECMAScript 的发展就再没有什么特别大的动静，新特性加入得悄无声息，如果不是特意去关注，开发者们甚至都搞不清当前所用的新特性到底是哪一版引入的内容。不少特性在 ES201…"}},{"node":{"id":"d936080e-981b-53b7-8a9d-4ac59e781ce4","frontmatter":{"title":"TypeScriptS + Vue 踩坑纪实","description":"坑这种东西，多踩踩就平了","from":null,"to":null,"tags":["typescript","vue"],"cover":{"publicURL":"/static/guide-for-vue-with-typescript-fe6f5086d26293f21adf217a84141fd6.jpg"},"series":"","draft":false},"fields":{"slug":"/blog/2017/10/26/guide-for-vue-with-typescript","type":"blog","date":"2017-10-25T16:00:00.000Z"},"excerpt":"TypeScript 这个磨人的小妖精讲到 TypeScript，那重点当然是在 Type 上。TypeScript 作为 JavaScript 的超集，在实现了主流 ECMAScript…"}},{"node":{"id":"bb2e9cf8-3bbe-5f7c-98d5-1fec33ba417f","frontmatter":{"title":"每天一点ES6(15)：Promise","description":"对你的承诺，永远不变","from":null,"to":null,"tags":["ecmascript","2015","es6","javascript","promise"],"cover":{"publicURL":"/static/es6daily-0950334fb8899f1006423341cbfeecb9.jpg"},"series":"es6daily","draft":false},"fields":{"slug":"/blog/2018/03/04/es6-daily-15-promise","type":"blog","date":"2018-03-03T16:00:00.000Z"},"excerpt":"写在前面Promise 大概是 ES6 中最为人熟知的内容之一了，时至今日它已经成为了异步操作中事实上的新标准。什么是 PromisePromise 和它的字面意思一样，代表着某种承诺，承诺未来某个时间会发生的事。Promise…"}},{"node":{"id":"16ce0730-d75b-5447-b6ea-98fbc60be827","frontmatter":{"title":"每天一点ES6(16)：Generator","description":"一起来摩擦摩擦发电吧","from":null,"to":null,"tags":["ecmascript","2015","es6","javascript","promise"],"cover":{"publicURL":"/static/es6daily-0950334fb8899f1006423341cbfeecb9.jpg"},"series":"es6daily","draft":false},"fields":{"slug":"/blog/2018/06/14/es6-daily-16-generator","type":"blog","date":"2018-06-13T16:00:00.000Z"},"excerpt":"什么是 Generator ？Generator 函数是 ES6 引入的一种异步编程解决方案，在之前讲Iterator和Promise的时候有提到过。Generator 从字面上理解，叫“生成器”，单看名字感觉和工厂函数有关，似乎是用来创建某些东西的。可以把 Generator…"}},{"node":{"id":"36af923e-bb47-52aa-96cd-e6a99513e3b1","frontmatter":{"title":"每天一点ES6(18)：Class","description":"这回总没人质疑 JS 不是面向对象了吧？","from":null,"to":null,"tags":["ecmascript","2015","es6","javascript","class"],"cover":{"publicURL":"/static/es6daily-0950334fb8899f1006423341cbfeecb9.jpg"},"series":"es6daily","draft":false},"fields":{"slug":"/blog/2018/12/17/es6-daily-18-class","type":"blog","date":"2018-12-16T16:00:00.000Z"},"excerpt":"过去从我们学习 JavaScript 的第一天起，我们就被告知，JavaScript 是面向对象的，虽然它的语法和传统的 C 风格相去甚远，甚至有人并不认可 JavaScript 是面向对象的。但不管怎么说，这并不影响我们使用 JavaScript…"}},{"node":{"id":"4cbe36e0-f1d8-5c77-bd3d-488364df8403","frontmatter":{"title":"除了 SSR，就没有别的办法了吗","description":"当 MVVM 遇上 SEO，该如何是好","from":null,"to":null,"tags":["static","site","gatsby","pug"],"cover":{"publicURL":"/static/explore-static-site-generation-c2ac5cf49eafd77a1b2ce1fab7f53515.jpg"},"series":"","draft":false},"fields":{"slug":"/blog/2019/02/07/explore-static-site-generation","type":"blog","date":"2019-02-06T16:00:00.000Z"},"excerpt":"SSR 出啥事了放心，SSR 没出事。写这篇博客并不是想说 SSR…"}},{"node":{"id":"2cbc576a-c00f-56b5-bfa6-7ef2d4422690","frontmatter":{"title":"每天一点ES6(19)：Module","description":"可能是 ES6 中对未来影响最大的一项改变","from":null,"to":null,"tags":["ecmascript","2015","es6","javascript","module","import","export"],"cover":{"publicURL":"/static/es6daily-0950334fb8899f1006423341cbfeecb9.jpg"},"series":"es6daily","draft":false},"fields":{"slug":"/blog/2018/12/19/es6-daily-19-module","type":"blog","date":"2018-12-18T16:00:00.000Z"},"excerpt":"模块化但凡有一定资历的开发者，对“模块化”的概念应该都非常熟悉了。C、PHP 有  、Java、Python 有  ，Ruby 有  ，连 CSS 都有  。然而 JavaScript 却一直都没有语言层面的模块化方案 —— 直到 ES…"}},{"node":{"id":"ba6e2937-ae6b-5c5c-9119-e7b307067954","frontmatter":{"title":"你可能已经知道的 ES 2018 和 2019","description":"好饭不怕晚","from":null,"to":null,"tags":["ecmascript","2018","2019"],"cover":{"publicURL":"/static/es2019-5646b4878e533cd7c725ce4c17984071.jpg"},"series":"","draft":false},"fields":{"slug":"/blog/2019/02/11/es2018-and-es2019","type":"blog","date":"2019-02-10T16:00:00.000Z"},"excerpt":"标准这事儿吧……ES 2019（ES 10）标准于年前正式发布，借此机会，我们来看看都有哪些特性有幸转正吧。顺带把 ES 2018 的内容也补一下。ECMAScript 标准的制定过程，自 2015 年大改，至今已经是第 5 个年头了，想必大家都心里有数了。与 Java…"}},{"node":{"id":"67e0382d-487f-5dc1-934d-03150e7d768d","frontmatter":{"title":"如何 Think in Hooks","description":"差不多是时候该换换脑子了","from":null,"to":null,"tags":["react","hooks"],"cover":{"publicURL":"/static/think-in-hooks-26d13ef2591ee05a3c4bba7fc34daa88.jpg"},"series":"","draft":false},"fields":{"slug":"/blog/2019/02/15/how-to-think-in-hooks","type":"blog","date":"2019-02-14T16:00:00.000Z"},"excerpt":"喜迎 Hooks正当中国人民还沉浸在过年的忙碌中，在世界的另一头，React 团队的小伙伴们一点也没闲着，他们写了 一篇博客 ，并借此正式发布了 Hooks —— 一个官方宣传了好久、开发者们也期待了好久的新特性。Hooks 正式发布于 v16.8.…"}},{"node":{"id":"90860267-81d0-59f9-864f-2fc7a381e411","frontmatter":{"title":"一个非著名前端开发者的 2016","description":"回顾 2016，是充实的一年，不负青春。2017 加油继续！","from":null,"to":null,"tags":["summary","2016","2017"],"cover":{"publicURL":"/static/summary-2016-d4bc85d6ff1aa8985e03c3875f90ea51.jpg"},"series":"summary","draft":false},"fields":{"slug":"/blog/2016/12/31/summary-2016","type":"blog","date":"2016-12-30T16:00:00.000Z"},"excerpt":"再见20162016年眼看着就要过去了，回顾这一年，感觉还是相当充实的一年，赶上了好时候，收获也不少。天时：这是最好的时代自2014年HTML…"}},{"node":{"id":"1d25cace-61d5-5c22-b434-7bdec32e4d99","frontmatter":{"title":"一个非著名前端开发者的 2017","description":"哎 ~ 又一年过去了","from":null,"to":null,"tags":["summary","2017","2018"],"cover":{"publicURL":"/static/summary-2017-0d96380257d25f6b398d9bc8e47af5a1.jpg"},"series":"summary","draft":false},"fields":{"slug":"/blog/2017/12/29/summary-2017","type":"blog","date":"2017-12-28T16:00:00.000Z"},"excerpt":"写在前面当我准备写这篇博客的时候，我突然意识到：麻蛋，又一年过去了，我又老了一岁，去年定的目标又有一部分要延期处理了。虽然年年都有被遗忘的小目标，但也还是有不少实现了的小目标的过去这一年2016 年是我正式参加工作的头一年，这一年里，我从一个只会 Bootstrap…"}},{"node":{"id":"6ad1f893-67c1-5a15-998c-10e7583b1d2f","frontmatter":{"title":"TradingView + WebSocket 脱坑指南","description":"让我来告诉你，K 线到底该怎么画","from":null,"to":null,"tags":["tradingview","chart","library","guide","websocket","webworker","ohlc","kchart"],"cover":{"publicURL":"/static/tradingview-1ceaf53d99815784a18273970e741bfd.jpg"},"series":"","draft":false},"fields":{"slug":"/blog/2018/09/22/tradingview-charting-library-simple-guide","type":"blog","date":"2018-09-21T16:00:00.000Z"},"excerpt":"0. 竟然被催更了前两天公司领导居然提到我的博客，说我最近懒了，不更新了……趁放假，赶紧更新一轮……等等，什么时候这变成工作了？1. TradingView 是个啥今天咱们说个比较特别的——TradingView，这是一个专业的图表库，专门做 K 线图的，而 K…"}},{"node":{"id":"cf6da5bc-cd0c-5983-8cc1-d86844f22178","frontmatter":{"title":"【译】React 如何区分 Class 和 Function？","description":"所谓的简单，只是因为有人帮你把复杂的问题给解决掉了","from":null,"to":null,"tags":["react"],"cover":{"publicURL":"/static/overreacted-9fbf74366dc5b9e4aab57572a9f0470d.jpg"},"series":"overreacted","draft":false},"fields":{"slug":"/blog/2019/03/06/how-does-react-tell-a-class-from-a-function","type":"blog","date":"2019-03-05T16:00:00.000Z"},"excerpt":"原文地址：How Does React Tell a Class from a Function?)原文作者：Dan Abramov让我们来看一下这个以函数形式定义的  组件：React 也支持将他定义成一个类：（直到 最近，这是使用 state…"}},{"node":{"id":"42927af1-290f-56d0-81fa-0ebe4101167b","frontmatter":{"title":"TypeScript 进门","description":"终于，可以比较放心的使用 TS 了","from":null,"to":null,"tags":["typescript"],"cover":{"publicURL":"/static/typescript-56ae6d6bf04b1d89cb44e68763f35699.jpg"},"series":"","draft":true},"fields":{"slug":"/blog/2019/05/06/typescript-beginner-guide","type":"blog","date":"2019-05-05T16:00:00.000Z"},"excerpt":"专业和业余的区别前端的低门槛，给很多人留下了「这是个能速成的高薪岗位」的印象，自学一个星期就能上手，一个月就能达到 6…"}},{"node":{"id":"503ee8c8-7050-523b-87f1-90f962181136","frontmatter":{"title":"Is CSS4 Ready","description":"好久没有听说关于 CSS 的更新了，CSS 还在更新吗","from":null,"to":null,"tags":["css"],"cover":{"publicURL":"/static/css4-a21bf2f730a43a221a47d5d8ffe18001.jpg"},"series":"","draft":true},"fields":{"slug":"/blog/2019/05/07/is-css4-ready","type":"blog","date":"2019-05-06T16:00:00.000Z"},"excerpt":"起源好久没有听说关于 CSS 的更新了，CSS 还在更新吗？传说中的 CSS 4 似乎就跟《钢铁侠4》一样，没有 CSS 4按照官方定义的标准，CSS 4 是不存在的，只有 CSS [模块名称] Level 4。别说 CSS 4 了，甚至连 CSS 3 都是误读。"}}]}},"pageContext":{"isCreatedByStatefulCreatePages":true}}